betterhtmlchunking/__init__.py
betterhtmlchunking/cli.py
betterhtmlchunking/logging_config.py
betterhtmlchunking/main.py
betterhtmlchunking/render_system.py
betterhtmlchunking/tree_regions_system.py
betterhtmlchunking/tree_representation.py
betterhtmlchunking/utils.py
betterhtmlchunking-0.9.6.dist-info/licenses/LICENSE
betterhtmlchunking-0.9.6.dist-info/METADATA
betterhtmlchunking-0.9.6.dist-info/WHEEL
betterhtmlchunking-0.9.6.dist-info/entry_points.txt
betterhtmlchunking-0.9.6.dist-info/top_level.txt
betterhtmlchunking-0.9.6.dist-info/RECORD
