Metadata-Version: 2.4
Name: betterhtmlchunking
Version: 0.9.6
Summary: A Python library for intelligent HTML segmentation and ROI extraction. It builds a DOM tree from raw HTML and extracts content-rich regions for efficient web scraping and analysis.
Author-email: "Carlos A. Planchón" <carlosandresplanchonprestes@gmail.com>
License-Expression: MIT
Project-URL: Repository, https://github.com/carlosplanchon/betterhtmlchunking
Project-URL: Issues, https://github.com/carlosplanchon/betterhtmlchunking/issues
Keywords: html,chunking,scraping,dom,roi,content extraction,web-scraping
Classifier: Intended Audience :: Developers
Classifier: Topic :: Software Development :: Libraries
Classifier: Programming Language :: Python :: 3
Classifier: Programming Language :: Python :: 3.12
Classifier: Programming Language :: Python :: 3.13
Classifier: Programming Language :: Python :: 3.14
Requires-Python: >=3.12
License-File: LICENSE
Requires-Dist: attrs
Requires-Dist: attrs-strict
Requires-Dist: beautifulsoup4
Requires-Dist: lxml
Requires-Dist: treelib
Requires-Dist: parsel_text
Requires-Dist: typer
Provides-Extra: dev
Requires-Dist: pytest>=9.0.2; extra == "dev"
Requires-Dist: pytest-cov>=7.0.0; extra == "dev"
Requires-Dist: ipython>=9.9.0; extra == "dev"
Requires-Dist: prettyprinter>=0.18.0; extra == "dev"
Dynamic: license-file
